lnet.cpython-37m-darwin.so
l_net-0.1.1.dist-info/LICENSE
l_net-0.1.1.dist-info/METADATA
l_net-0.1.1.dist-info/WHEEL
l_net-0.1.1.dist-info/top_level.txt
l_net-0.1.1.dist-info/RECORD
