Metadata-Version: 2.1
Name: l-net
Version: 0.1.1
Summary: Adds the ability to combine l1 to l10 penalties in regression extending the elastic-net.
Home-page: https://github.com/austindavidbrown/l-net
Author: Austin David Brown
Author-email: brow5079@umn.edu
License: GPL3
Platform: UNKNOWN
